rcache.py
rcache-1.0.0.dist-info/LICENSE
rcache-1.0.0.dist-info/WHEEL
rcache-1.0.0.dist-info/METADATA
rcache-1.0.0.dist-info/RECORD
